data_downloader/__init__.py
data_downloader/downloader.py
data_downloader/parse_urls.py
data_downloader/services/__init__.py
data_downloader/services/licsar.py
data_downloader/services/sentinel_aux.py
data_downloader/services/hyp3/__init__.py
data_downloader/services/hyp3/constants.py
data_downloader/services/hyp3/hyp3.py
data_downloader/utils/__init__.py
data_downloader/utils/pairs.py
data_downloader-1.2.dist-info/LICENSE
data_downloader-1.2.dist-info/METADATA
data_downloader-1.2.dist-info/WHEEL
data_downloader-1.2.dist-info/top_level.txt
data_downloader-1.2.dist-info/RECORD
