Metadata-Version: 2.1
Name: data_downloader
Version: 1.2
Summary: Make downloading scientific data much easier
Home-page: https://github.com/Fanchengyan/data_downloader
Author: fanchegyan
Author-email: fanchy14@lzu.edu.cn
Classifier: Programming Language :: Python :: 3
Classifier: License :: OSI Approved :: MIT License
Classifier: Operating System :: OS Independent
Requires-Python: >=3.8
License-File: LICENSE
Requires-Dist: httpx >=0.4.0
Requires-Dist: requests
Requires-Dist: tqdm
Requires-Dist: setuptools
Requires-Dist: beautifulsoup4
Requires-Dist: nest-asyncio
Requires-Dist: python-dateutil
Requires-Dist: browser-cookie3
Requires-Dist: hyp3-sdk
Requires-Dist: pandas
